.gitignore
LICENSE
MANIFEST.in
README.md
README.rst
requirements.txt
setup.py
test.yml
viman/__init__.py
viman/vimanApp.py
viman/vimanArgParser.py
viman/vimanExcept.py
viman/vimanGitWrapper.py
viman/vimanUtils.py
viman/vimanYamlWrapper.py
viman.egg-info/PKG-INFO
viman.egg-info/SOURCES.txt
viman.egg-info/dependency_links.txt
viman.egg-info/entry_points.txt
viman.egg-info/not-zip-safe
viman.egg-info/requires.txt
viman.egg-info/top_level.txt