Metadata-Version: 1.2
Name: viman
Version: 0.0.14
Summary: The vim plugin manager based on git and pathogen!
Home-page: https://github.com/Shylock-Hg/viman.git
Author: Shylock Hg
Author-email: tcath2s@gmail.com
License: GPL-3.0
Platform: UNKNOWN
Requires-Python: >=3.3
